nonebot_plugin_word_bank3/__init__.py
nonebot_plugin_word_bank3/data_source.py
nonebot_plugin_word_bank3/models/typing_models.py
nonebot_plugin_word_bank3/models/word_bank.py
nonebot_plugin_word_bank3/models/word_bank_data.py
nonebot_plugin_word_bank3/utils.py
nonebot_plugin_word_bank3-0.1.0a3.dist-info/LICENSE
nonebot_plugin_word_bank3-0.1.0a3.dist-info/WHEEL
nonebot_plugin_word_bank3-0.1.0a3.dist-info/METADATA
nonebot_plugin_word_bank3-0.1.0a3.dist-info/RECORD
