Metadata-Version: 2.1
Name: nonebot-plugin-word-bank3
Version: 0.1.0a3
Summary: 有数据问答插件
License: MIT
Author: kexue
Author-email: x@kexue.io
Requires-Python: >=3.8,<4.0
Classifier: License :: OSI Approved :: MIT License
Classifier: Programming Language :: Python :: 3
Classifier: Programming Language :: Python :: 3.10
Classifier: Programming Language :: Python :: 3.8
Classifier: Programming Language :: Python :: 3.9
Requires-Dist: nonebot-adapter-onebot (>=2.0.0-beta.1)
Requires-Dist: nonebot-plugin-tortoise-orm (>=0.0.1-alpha.3,<0.0.2)
Requires-Dist: nonebot2 (>=2.0.0-beta.2)
